docs/source/conf.py
easy_mpl/__init__.py
easy_mpl/_bar.py
easy_mpl/_box.py
easy_mpl/_circular_bar_plot.py
easy_mpl/_contour.py
easy_mpl/_dumbell.py
easy_mpl/_hist.py
easy_mpl/_imshow.py
easy_mpl/_lollipop.py
easy_mpl/_main.py
easy_mpl/_parallel_coords.py
easy_mpl/_pie.py
easy_mpl/_regplot.py
easy_mpl/_ridge.py
easy_mpl/_scatter.py
easy_mpl/_spider.py
easy_mpl/_surf.py
easy_mpl/_taylor_plot.py
easy_mpl/_violin.py
easy_mpl/utils.py
easy_mpl-0.21.5.dist-info/licenses/LICENSE.txt
examples/bar_chart.py
examples/boxplot.py
examples/circular_bar_plot.py
examples/contour.py
examples/dumbell.py
examples/hist.py
examples/imshow.py
examples/junk.py
examples/lollipop_plot.py
examples/marginal_plots.py
examples/neural_network.py
examples/parallel_coordinates.py
examples/pie.py
examples/plot.py
examples/reg_plot.py
examples/ridge.py
examples/scatter.py
examples/spider_plot.py
examples/taylor_plot.py
examples/violin.py
tests/__init__.py
tests/junk.py
tests/test_bar.py
tests/test_box.py
tests/test_circular_bar_plot.py
tests/test_contour.py
tests/test_dumbell.py
tests/test_hist.py
tests/test_imshow.py
tests/test_lollipop.py
tests/test_main.py
tests/test_parallel_coords.py
tests/test_pie.py
tests/test_regplot.py
tests/test_ridge.py
tests/test_scatter.py
tests/test_spider.py
tests/test_surf.py
tests/test_taylor_plot.py
tests/test_utils.py
tests/test_violin.py
venv/bin/activate_this.py
easy_mpl-0.21.5.dist-info/METADATA
easy_mpl-0.21.5.dist-info/WHEEL
easy_mpl-0.21.5.dist-info/top_level.txt
easy_mpl-0.21.5.dist-info/RECORD
