Metadata-Version: 2.4
Name: easy_mpl
Version: 0.21.5
Summary: one stop shop for matplotlib plots
Author-email: Sara Iftikhar <sara.rwpk@gmail.com>
Project-URL: Homepage, https://github.com/Sara-Iftikhar/easy_mpl
Classifier: Development Status :: 4 - Beta
Classifier: Natural Language :: English
Classifier: Intended Audience :: Science/Research
Classifier: Intended Audience :: Developers
Classifier: Operating System :: Microsoft :: Windows
Classifier: Operating System :: POSIX :: Linux
Classifier: Programming Language :: Python :: 3
Classifier: Programming Language :: Python :: 3.5
Classifier: Programming Language :: Python :: 3.6
Classifier: Programming Language :: Python :: 3.7
Classifier: Programming Language :: Python :: 3.8
Classifier: Programming Language :: Python :: 3.9
Requires-Python: >=3.5
License-File: LICENSE.txt
Requires-Dist: matplotlib<3.11.0,>=3.3.0
Provides-Extra: all
Requires-Dist: matplotlib<3.11.0,>=3.3.0; extra == "all"
Requires-Dist: pandas<2.3.0,>=0.23.3; extra == "all"
Requires-Dist: scipy; extra == "all"
Dynamic: license-file
